Metadata-Version: 1.0
Name: xqys
Version: 1.1
Summary: Deep Learning Framework
Home-page: https://github.com/moh833/XQYS
Author: Mohamed Medhat
Author-email: mohamed.medhat8334@gmail.com
License: UNKNOWN
Platform: UNKNOWN
